propdayscov/__init__.py
propdayscov/propdayscov.py
propdayscov-1.2.0.dist-info/LICENSE
propdayscov-1.2.0.dist-info/METADATA
propdayscov-1.2.0.dist-info/WHEEL
propdayscov-1.2.0.dist-info/top_level.txt
propdayscov-1.2.0.dist-info/RECORD
