Metadata-Version: 2.1
Name: propdayscov
Version: 1.2.0
Summary: A package for calculating medication PDC.
Home-page: https://github.com/ReppCodes/propdayscov
Author: Andrew Repp
Author-email: ajrepp1@gmail.com
License: UNKNOWN
Platform: UNKNOWN
Classifier: Programming Language :: Python :: 3
Classifier: License :: OSI Approved :: MIT License
Classifier: Operating System :: OS Independent
License-File: LICENSE
